README.rst
setup.py
plato_cat/__init__.py
plato_cat/cmd.py
plato_cat.egg-info/PKG-INFO
plato_cat.egg-info/SOURCES.txt
plato_cat.egg-info/dependency_links.txt
plato_cat.egg-info/entry_points.txt
plato_cat.egg-info/requires.txt
plato_cat.egg-info/top_level.txt
plato_cat/alerts/__init__.py
plato_cat/alerts/console.py
plato_cat/alerts/onealert.py
plato_cat/alerts/slack.py
plato_cat/cases/__init__.py
plato_cat/cases/eip.py
plato_cat/cases/image.py
plato_cat/cases/instance.py
plato_cat/cases/instance_type.py
plato_cat/cases/job.py
plato_cat/cases/key_pair.py
plato_cat/cases/monitor.py
plato_cat/cases/network.py
plato_cat/cases/operation.py
plato_cat/cases/quota.py
plato_cat/cases/snapshot.py
plato_cat/cases/volume.py
plato_cat/sdk/__init__.py
plato_cat/sdk/codes.py
plato_cat/sdk/conn.py
plato_cat/sdk/errors.py
plato_cat/sdk/regions.py
plato_cat/sdk/actions/__init__.py
plato_cat/sdk/actions/api.py
plato_cat/sdk/actions/instances.py
plato_cat/sdk/actions/networks.py
plato_cat/sdk/actions/params.py
plato_cat/sdk/actions/volumes.py