Metadata-Version: 1.0
Name: plato-cat
Version: 0.4.7
Summary: a cat
Home-page: http://plato_cat.com
Author: piaoyuankui@le.com
Author-email: UNKNOWN
License: MIT
Platform: UNKNOWN
